{                                                                                                                                                                                                                                                              
    "resources": [                                                                                                                                                                                                                                             
        {                                                                                                                                                                                                                                                      
            "name": "manifest.json"                                                                                                                                                                                                                            
        },                                                                                                                                                                                                                                                     
        {                                                                                                                                                                                                                                                      
            "name": "i18n/i18n.properties",                                                                                                                                                                                                                    
            "raw": "i18n/i18n.properties"                                                                                                                                                                                                                      
        },                                                                                                                                                                                                                                                     
        {                                                                                                                                                                                                                                                      
            "name": "model/models.js"                                                                                                                                                                                                                          
        },                                                                                                                                                                                                                                                     
        {                                                                                                                                                                                                                                                      
            "name": "model/formatter.js"                                                                                                                                                                                                                       
        },                                                                                                                                                                                                                                                     
        {                                                                                                                                                                                                                                                      
            "name": "localService/mockserver.js"                                                                                                                                                                                                               
        },                                                                                                                                                                                                                                                     
        {                                                                                                                                                                                                                                                      
            "name": "controller/NotFound.controller.js"                                                                                                                                                                                                        
        },                                                                                                                                                                                                                                                     
        {                                                                                                                                                                                                                                                      
            "name": "controller/MainReport.controller.js"                                                                                                                                                                                                      
        },                                                                                                                                                                                                                                                     
        {                                                                                                                                                                                                                                                      
            "name": "controller/JournalEntries.controller.js"                                                                                                                                                                                                  
        },                                                                                                                                                                                                                                                     
        {                                                                                                                                                                                                                                                      
            "name": "controller/ErrorHandler.js"                                                                                                                                                                                                               
        },                                                                                                                                                                                                                                                     
        {                                                                                                                                                                                                                                                      
            "name": "controller/BaseController.js"                                                                                                                                                                                                             
        },                                                                                                                                                                                                                                                     
        {                                                                                                                                                                                                                                                      
            "name": "controller/App.controller.js"                                                                                                                                                                                                             
        },                                                                                                                                                                                                                                                     
        {                                                                                                                                                                                                                                                      
            "name": "Component.js"                                                                                                                                                                                                                             
        },                                                                                                                                                                                                                                                     
        {                                                                                                                                                                                                                                                      
            "name": "manifest-bundle.zip"                                                                                                                                                                                                                      
        },                                                                                                                                                                                                                                                     
        {                                                                                                                                                                                                                                                      
            "name": "Component-preload.js",                                                                                                                                                                                                                    
            "merged": true                                                                                                                                                                                                                                     
        },                                                                                                                                                                                                                                                     
        {                                                                                                                                                                                                                                                      
            "name": "model/models-dbg.js",                                                                                                                                                                                                                     
            "isDebug": true                                                                                                                                                                                                                                    
        },                                                                                                                                                                                                                                                     
        {                                                                                                                                                                                                                                                      
            "name": "model/formatter-dbg.js",                                                                                                                                                                                                                  
            "isDebug": true                                                                                                                                                                                                                                    
        },                                                                                                                                                                                                                                                     
        {                                                                                                                                                                                                                                                      
            "name": "localService/mockserver-dbg.js",                                                                                                                                                                                                          
            "isDebug": true                                                                                                                                                                                                                                    
        },                                                                                                                                                                                                                                                     
        {                                                                                                                                                                                                                                                      
            "name": "controller/NotFound-dbg.controller.js",                                                                                                                                                                                                   
            "isDebug": true                                                                                                                                                                                                                                    
        },                                                                                                                                                                                                                                                     
        {                                                                                                                                                                                                                                                      
            "name": "controller/MainReport-dbg.controller.js",                                                                                                                                                                                                 
            "isDebug": true                                                                                                                                                                                                                                    
        },                                                                                                                                                                                                                                                     
        {                                                                                                                                                                                                                                                      
            "name": "controller/JournalEntries-dbg.controller.js",                                                                                                                                                                                             
            "isDebug": true                                                                                                                                                                                                                                    
        },                                                                                                                                                                                                                                                     
        {                                                                                                                                                                                                                                                      
            "name": "controller/ErrorHandler-dbg.js",                                                                                                                                                                                                          
            "isDebug": true                                                                                                                                                                                                                                    
        },                                                                                                                                                                                                                                                     
        {                                                                                                                                                                                                                                                      
            "name": "controller/BaseController-dbg.js",                                                                                                                                                                                                        
            "isDebug": true                                                                                                                                                                                                                                    
        },                                                                                                                                                                                                                                                     
        {                                                                                                                                                                                                                                                      
            "name": "controller/App-dbg.controller.js",                                                                                                                                                                                                        
            "isDebug": true                                                                                                                                                                                                                                    
        },                                                                                                                                                                                                                                                     
        {                                                                                                                                                                                                                                                      
            "name": "Component-dbg.js",                                                                                                                                                                                                                        
            "isDebug": true                                                                                                                                                                                                                                    
        },                                                                                                                                                                                                                                                     
        {                                                                                                                                                                                                                                                      
            "name": "../../../../../sap-ui-version.json"                                                                                                                                                                                                       
        },                                                                                                                                                                                                                                                     
        {                                                                                                                                                                                                                                                      
            "name": "neo-app.json"                                                                                                                                                                                                                             
        },                                                                                                                                                                                                                                                     
        {                                                                                                                                                                                                                                                      
            "name": "di.code-validation.core_issues.json"                                                                                                                                                                                                      
        },                                                                                                                                                                                                                                                     
        {                                                                                                                                                                                                                                                      
            "name": "view/NotFound.view.xml"                                                                                                                                                                                                                   
        },                                                                                                                                                                                                                                                     
        {                                                                                                                                                                                                                                                      
            "name": "view/MainReport.view.xml"                                                                                                                                                                                                                 
        },                                                                                                                                                                                                                                                     
        {                                                                                                                                                                                                                                                      
            "name": "view/JournalEntries.view.xml"                                                                                                                                                                                                             
        },                                                                                                                                                                                                                                                     
        {                                                                                                                                                                                                                                                      
            "name": "view/App.view.xml"                                                                                                                                                                                                                        
        },                                                                                                                                                                                                                                                     
        {                                                                                                                                                                                                                                                      
            "name": "localService/metadata.xml"                                                                                                                                                                                                                
        },                                                                                                                                                                                                                                                     
        {                                                                                                                                                                                                                                                      
            "name": "fragment/BusyDialog.fragment.xml"                                                                                                                                                                                                         
        },                                                                                                                                                                                                                                                     
        {                                                                                                                                                                                                                                                      
            "name": "css/style.css"                                                                                                                                                                                                                            
        },                                                                                                                                                                                                                                                     
        {                                                                                                                                                                                                                                                      
            "name": "annotations/annotation1.xml"                                                                                                                                                                                                              
        }                                                                                                                                                                                                                                                      
    ]                                                                                                                                                                                                                                                          
}                                                                                                                                                                                                                                                              