<mvc:View controllerName="ey.sap.fin.cs.hierarchyReport.controller.hierarchy" xmlns="sap.m" xmlns:mvc="sap.ui.core.mvc"                                                                                                                                        
	xmlns:uxap="sap.uxap" xmlns:smartFilterBar="sap.ui.comp.smartfilterbar" xmlns:smartTable="sap.ui.comp.smarttable" xmlns:table="sap.ui.table"                                                                                                                  
	xmlns:core="sap.ui.core" xmlns:f="sap.f" xmlns:sv="sap.ui.comp.smartvariants" xmlns:layout="sap.ui.layout"                                                                                                                                                    
	xmlns:customData="http://schemas.sap.com/sapui5/extension/sap.ui.core.CustomData/1">                                                                                                                                                                          
	<uxap:ObjectPageLayout id="idEquityReconObjectPageLayout" showAnchorBarPopover="false" upperCaseAnchorBar="false">                                                                                                                                            
		<uxap:headerTitle>                                                                                                                                                                                                                                           
			<uxap:ObjectPageDynamicHeaderTitle>                                                                                                                                                                                                                         
				<uxap:heading>                                                                                                                                                                                                                                             
					<sv:SmartVariantManagement id="idEquityReconSmartVariantMgmt"                                                                                                                                                                                             
						persistencyKey="ey.sap.fin.cs.equityreconciliation.controller.controller.MainReport" showShare="true" showExecuteOnSelection="true"                                                                                                                      
						entitySet="xEY1xSAV_C_Reconciliation"/>                                                                                                                                                                                                                  
				</uxap:heading>                                                                                                                                                                                                                                            
			</uxap:ObjectPageDynamicHeaderTitle>                                                                                                                                                                                                                        
		</uxap:headerTitle>                                                                                                                                                                                                                                          
		<uxap:headerContent>                                                                                                                                                                                                                                         
			<smartFilterBar:SmartFilterBar id="idsmartFilterBar" smartVariant="idEquityReconSmartVariantMgmt"                                                                                                                                                           
				persistencyKey="ey.sap.fin.cs.equityreconciliation.controller.MainReport.FilterBar" considerSelectionVariants="true"                                                                                                                                       
				entitySet="xEY1xSAV_C_Reconciliation" search="onSearchButtonPressed" enableBasicSearch="false" useToolbar="false"                                                                                                                                          
				basicSearchFieldName="GLAccount,AccountClassCode,GLAccount" pendingChange="onRbUnitChange" beforeVariantSave="onBeforeVariantSaveFilterBar"                                                                                                                
				afterVariantLoad="onAfterVariantLoadFilterBar">                                                                                                                                                                                                            
				<smartFilterBar:controlConfiguration>                                                                                                                                                                                                                      
					<smartFilterBar:ControlConfiguration id="idRbunit" key="ConsolidationUnit" label="{i18n>labelConsUnit}" mandatory="mandatory"                                                                                                                             
						hasValueHelpDialog="true" visibleInAdvancedArea="true" displayBehaviour="descriptionAndId" index="1">                                                                                                                                                    
						<smartFilterBar:customControl>                                                                                                                                                                                                                           
							<ComboBox id="idConsUnit" items="{ path: '/ConsolidationUnit'}" change="onConsUnitChange" showSecondaryValues="true" valueState='None'                                                                                                                  
								filterSecondaryValues="true">                                                                                                                                                                                                                          
								<core:ListItem id="idConsUnitLI" key="{ConsolidationUnit}" text="{ConsolidationUnit_Text}" additionalText="{ConsolidationUnit}"/>                                                                                                                      
							</ComboBox>                                                                                                                                                                                                                                             
						</smartFilterBar:customControl>                                                                                                                                                                                                                          
					</smartFilterBar:ControlConfiguration>                                                                                                                                                                                                                    
					<smartFilterBar:ControlConfiguration id="idRyear" key="FiscalYear" label="{i18n>labelFiscalYear}" visibleInAdvancedArea="true" index="2"                                                                                                                  
						mandatory="mandatory">                                                                                                                                                                                                                                   
						<smartFilterBar:customControl>                                                                                                                                                                                                                           
							<DatePicker id="idFiscalYearFilter" displayFormat="yyyy" change="onChangeDatePickerFilter"/>                                                                                                                                                            
						</smartFilterBar:customControl>                                                                                                                                                                                                                          
					</smartFilterBar:ControlConfiguration>                                                                                                                                                                                                                    
					<smartFilterBar:ControlConfiguration id="idIntention" key="Intention" label="{i18n>labelIntention}" hasValueHelpDialog="true"                                                                                                                             
						visibleInAdvancedArea="true" displayBehaviour="descriptionAndId" index="3">                                                                                                                                                                              
						<smartFilterBar:customControl>                                                                                                                                                                                                                           
							<ComboBox id="idIntentionComboBox" items="{intentionVHModel>/results}" change="onChangeIntentionComboBox" showSecondaryValues="true"                                                                                                                    
								valueState='None' filterSecondaryValues="true">                                                                                                                                                                                                        
								<core:ListItem id="idIntentionComboBoxLI" key="{intentionVHModel>Intent}" text="{intentionVHModel>IntentDescription}"                                                                                                                                  
									additionalText="{intentionVHModel>ConsolidationUnit}"/>                                                                                                                                                                                               
							</ComboBox>                                                                                                                                                                                                                                             
						</smartFilterBar:customControl>                                                                                                                                                                                                                          
					</smartFilterBar:ControlConfiguration>                                                                                                                                                                                                                    
					<smartFilterBar:ControlConfiguration id="idPeriodFrom" key="PeriodFrom" label="{i18n>labelPeriodFrom}" index="4">                                                                                                                                         
						<smartFilterBar:customControl>                                                                                                                                                                                                                           
							<Input id="idPeriodFromInput" type="Number" maxLength="3" value="1" editable="false"/>                                                                                                                                                                  
						</smartFilterBar:customControl>                                                                                                                                                                                                                          
					</smartFilterBar:ControlConfiguration>                                                                                                                                                                                                                    
					<smartFilterBar:ControlConfiguration id="idPeriodTo" key="PeriodTo" label="{i18n>labelPeriodTo}" index="5">                                                                                                                                               
						<smartFilterBar:customControl>                                                                                                                                                                                                                           
							<Input id="idPeriodToInput" type="Number" maxLength="3" value="12" liveChange="onLiveChangePeriodTo"/>                                                                                                                                                  
						</smartFilterBar:customControl>                                                                                                                                                                                                                          
					</smartFilterBar:ControlConfiguration>                                                                                                                                                                                                                    
					<smartFilterBar:ControlConfiguration id="idCurrType" key="CurrencyType" label="{i18n>labelCurrency}" mandatory="mandatory"                                                                                                                                
						hasValueHelpDialog="true" visibleInAdvancedArea="true" displayBehaviour="descriptionAndId" index="6" visible="false">                                                                                                                                    
						<smartFilterBar:customControl>                                                                                                                                                                                                                           
							<ComboBox id="idCurrency" items="{currLocalGroupVHModel>/results}" showSecondaryValues="false">                                                                                                                                                         
								<core:ListItem id="idLocalLI" key="{currLocalGroupVHModel>Currency}"                                                                                                                                                                                   
									text="{currLocalGroupVHModel>CurrencyType} ({currLocalGroupVHModel>Currency})" additionalText="{currLocalGroupVHModel>CurrencyType}"/>                                                                                                                
							</ComboBox>                                                                                                                                                                                                                                             
						</smartFilterBar:customControl>                                                                                                                                                                                                                          
					</smartFilterBar:ControlConfiguration>                                                                                                                                                                                                                    
					<smartFilterBar:ControlConfiguration id="idHierTypeCC" key="key" label="{i18n>labelHierType}" mandatory="mandatory"                                                                                                                                       
						hasValueHelpDialog="true" visibleInAdvancedArea="true" displayBehaviour="descriptionAndId" index="7">                                                                                                                                                    
						<smartFilterBar:customControl>                                                                                                                                                                                                                           
							<ComboBox id="idHierType" items="{hierVHModel>/}" showSecondaryValues="false" change="onChangeHierTypeCB">                                                                                                                                              
								<core:ListItem id="idHierTypLI" key="{hierVHModel>key}" text="{hierVHModel>name}"/>                                                                                                                                                                    
							</ComboBox>                                                                                                                                                                                                                                             
						</smartFilterBar:customControl>                                                                                                                                                                                                                          
					</smartFilterBar:ControlConfiguration>                                                                                                                                                                                                                    
					<smartFilterBar:ControlConfiguration id="idHierCatText" key="HierarchyId" label="{i18n>labelHierId}" index="8">                                                                                                                                           
						<smartFilterBar:customControl>                                                                                                                                                                                                                           
							<Input id="idHierCatTextInpt" showSuggestion="true" suggestionItems="{hierarCatModel>/}" showValueHelp="true"                                                                                                                                           
								valueHelpRequest="onValueHelpRequested" change="onChangeHierId">                                                                                                                                                                                       
								<suggestionItems>                                                                                                                                                                                                                                      
									<core:ListItem key="{hierarCatModel>HierarchyId}" text="{hierarCatModel>HierarchyId}" additionalText="{hierarCatModel>HierarchyText}"/>                                                                                                               
								</suggestionItems>                                                                                                                                                                                                                                     
							</Input>                                                                                                                                                                                                                                                
						</smartFilterBar:customControl>                                                                                                                                                                                                                          
					</smartFilterBar:ControlConfiguration>                                                                                                                                                                                                                    
				</smartFilterBar:controlConfiguration>                                                                                                                                                                                                                     
			</smartFilterBar:SmartFilterBar>                                                                                                                                                                                                                            
		</uxap:headerContent>                                                                                                                                                                                                                                        
		<uxap:sections>                                                                                                                                                                                                                                              
			<uxap:ObjectPageSection titleUppercase="false" title="{i18n>FSItemVHText}">                                                                                                                                                                                 
				<uxap:subSections>                                                                                                                                                                                                                                         
					<uxap:ObjectPageSubSection title="{i18n>FSItemVHText}" titleUppercase="false">                                                                                                                                                                            
						<smartTable:SmartTable id="idTRFMainRepSmartTable" tableType="TreeTable" showFullScreenButton="true" showVariantManagement="false"                                                                                                                       
							useVariantManagement="false" useTablePersonalisation="false" editTogglable="false" enableAutoBinding="false" entitySet="HierDatModel>/"                                                                                                                 
							class="sapUiResponsiveContentPadding" dataReceived="onDataReceivedSmartTable" useExportToExcel="false">                                                                                                                                                 
							<smartTable:customToolbar>                                                                                                                                                                                                                              
								<Toolbar id="idCustomToolbar1">                                                                                                                                                                                                                        
									<Title text="{i18n>fsItemTabTitle}"></Title>                                                                                                                                                                                                          
									<ToolbarSpacer id="idToolbarSpacerTRF"/>                                                                                                                                                                                                              
									<Button id="idAdjustLCCol" icon="sap-icon://resize-horizontal" tooltip="{i18n>optimizeColumnsWidthBtnTxt}" press="onAdjustTableCol"/>                                                                                                                 
								</Toolbar>                                                                                                                                                                                                                                             
							</smartTable:customToolbar>                                                                                                                                                                                                                             
							<table:TreeTable id="idTreeHierFSItem" rows="{path:'HierDatModel>/', parameters: {arrayNames:['childs']}}" selectionMode="None"                                                                                                                         
								enableSelectAll="false" visibleRowCountMode="Auto" toggleOpenState="onUpdateRows">                                                                                                                                                                     
								<table:Column autoResizable="true" hAlign="Left">                                                                                                                                                                                                      
									<Label text="{i18n>columnHeaderFinStatItem}" tooltip="{i18n>columnHeaderFSItem}" textAlign="Left"/>                                                                                                                                                   
									<table:template>                                                                                                                                                                                                                                      
										<Text text="{HierDatModel>NodeLowValue} ({HierDatModel>NodeLowValueText})" tooltip="{HierDatModel>NodeLowValue}" wrapping="false"/>                                                                                                                  
									</table:template>                                                                                                                                                                                                                                     
								</table:Column>                                                                                                                                                                                                                                        
								<table:Column autoResizable="true" hAlign="End">                                                                                                                                                                                                       
									<Label text="{i18n>columnHeaderGAAPOB}" tooltip="{i18n>columnHeaderGAAPOB}" textAlign="Right"/>                                                                                                                                                       
									<table:template>                                                                                                                                                                                                                                      
										<Text                                                                                                                                                                                                                                                
											text="{parts : [{path:'HierDatModel>GaapOpeningBalance'}, {path:'HierDatModel>MainCurrency'}],type: 'sap.ui.model.type.Currency',formatOptions:{showMeasure: false}}"                                                                               
											wrapping="false"                                                                                                                                                                                                                                    
											tooltip="{parts : [{path:'HierDatModel>GaapOpeningBalance'}, {path:'HierDatModel>MainCurrency'}],type: 'sap.ui.model.type.Currency',formatOptions:{showMeasure: false}}"/>                                                                          
									</table:template>                                                                                                                                                                                                                                     
								</table:Column>                                                                                                                                                                                                                                        
								<table:Column autoResizable="true" hAlign="End">                                                                                                                                                                                                       
									<Label text="{i18n>columnHeaderGAAPYB}" tooltip="{i18n>columnHeaderGAAPYB}" textAlign="Right"/>                                                                                                                                                       
									<table:template>                                                                                                                                                                                                                                      
										<Text                                                                                                                                                                                                                                                
											text="{parts : [{path:'HierDatModel>GaapYearBalance'}, {path:'HierDatModel>MainCurrency'}],type: 'sap.ui.model.type.Currency',formatOptions:{showMeasure: false}}"                                                                                  
											wrapping="false"                                                                                                                                                                                                                                    
											tooltip="{parts : [{path:'HierDatModel>GaapYearBalance'}, {path:'HierDatModel>MainCurrency'}],type: 'sap.ui.model.type.Currency',formatOptions:{showMeasure: false}}"/>                                                                             
									</table:template>                                                                                                                                                                                                                                     
								</table:Column>                                                                                                                                                                                                                                        
								<table:Column autoResizable="true" hAlign="End">                                                                                                                                                                                                       
									<Label text="{i18n>columnHeaderGAAPCTA}" tooltip="{i18n>columnHeaderGAAPCTA}" textAlign="Right"/>                                                                                                                                                     
									<table:template>                                                                                                                                                                                                                                      
										<Text wrapping="false"                                                                                                                                                                                                                               
											tooltip="{parts : [{path:'HierDatModel>GaapCTA'}, {path:'HierDatModel>MainCurrency'}],type: 'sap.ui.model.type.Currency',formatOptions:{showMeasure: false}}"                                                                                       
											text="{parts : [{path:'HierDatModel>GaapCTA'}, {path:'HierDatModel>MainCurrency'}],type: 'sap.ui.model.type.Currency',formatOptions:{showMeasure: false}}"/>                                                                                        
									</table:template>                                                                                                                                                                                                                                     
								</table:Column>                                                                                                                                                                                                                                        
								<table:Column autoResizable="true" hAlign="End">                                                                                                                                                                                                       
									<Label text="{i18n>columnHeaderGAAPCB}" tooltip="{i18n>columnHeaderGAAPCB}" textAlign="Right"/>                                                                                                                                                       
									<table:template>                                                                                                                                                                                                                                      
										<Text wrapping="false"                                                                                                                                                                                                                               
											tooltip="{parts : [{path:'HierDatModel>GaapClosingBalance'}, {path:'HierDatModel>MainCurrency'}],type: 'sap.ui.model.type.Currency',formatOptions:{showMeasure: false}}"                                                                            
											text="{parts : [{path:'HierDatModel>GaapClosingBalance'}, {path:'HierDatModel>MainCurrency'}],type: 'sap.ui.model.type.Currency',formatOptions:{showMeasure: false}}"/>                                                                             
									</table:template>                                                                                                                                                                                                                                     
								</table:Column>                                                                                                                                                                                                                                        
								<table:Column autoResizable="true" hAlign="End">                                                                                                                                                                                                       
									<Label text="{i18n>columnHeaderG2SPL}" tooltip="{i18n>columnHeaderG2SPL}" textAlign="Right"/>                                                                                                                                                         
									<table:template>                                                                                                                                                                                                                                      
										<Text wrapping="false"                                                                                                                                                                                                                               
											tooltip="{parts : [{path:'HierDatModel>GaapToStatPL'}, {path:'HierDatModel>MainCurrency'}],type: 'sap.ui.model.type.Currency',formatOptions:{showMeasure: false}}"                                                                                  
											text="{parts : [{path:'HierDatModel>GaapToStatPL'}, {path:'HierDatModel>MainCurrency'}],type: 'sap.ui.model.type.Currency',formatOptions:{showMeasure: false}}"/>                                                                                   
									</table:template>                                                                                                                                                                                                                                     
								</table:Column>                                                                                                                                                                                                                                        
								<table:Column autoResizable="true" hAlign="End">                                                                                                                                                                                                       
									<Label text="{i18n>columnHeaderG2SPerm}" tooltip="{i18n>columnHeaderG2SPerm}" textAlign="Right"/>                                                                                                                                                     
									<table:template>                                                                                                                                                                                                                                      
										<Text wrapping="false"                                                                                                                                                                                                                               
											tooltip="{parts : [{path:'HierDatModel>GaapToStatPmnt'}, {path:'HierDatModel>MainCurrency'}],type: 'sap.ui.model.type.Currency',formatOptions:{showMeasure: false}}"                                                                                
											text="{parts : [{path:'HierDatModel>GaapToStatPmnt'}, {path:'HierDatModel>MainCurrency'}],type: 'sap.ui.model.type.Currency',formatOptions:{showMeasure: false}}"/>                                                                                 
									</table:template>                                                                                                                                                                                                                                     
								</table:Column>                                                                                                                                                                                                                                        
								<table:Column autoResizable="true" hAlign="End">                                                                                                                                                                                                       
									<Label text="{i18n>columnHeaderG2SEq}" tooltip="{i18n>columnHeaderG2SEq}" textAlign="Right"/>                                                                                                                                                         
									<table:template>                                                                                                                                                                                                                                      
										<Text wrapping="false"                                                                                                                                                                                                                               
											tooltip="{parts : [{path:'HierDatModel>GaapToStatEQ'}, {path:'HierDatModel>MainCurrency'}],type: 'sap.ui.model.type.Currency',formatOptions:{showMeasure: false}}"                                                                                  
											text="{parts : [{path:'HierDatModel>GaapToStatEQ'}, {path:'HierDatModel>MainCurrency'}],type: 'sap.ui.model.type.Currency',formatOptions:{showMeasure: false}}"/>                                                                                   
									</table:template>                                                                                                                                                                                                                                     
								</table:Column>                                                                                                                                                                                                                                        
								<table:Column autoResizable="true" hAlign="End">                                                                                                                                                                                                       
									<Label text="{i18n>columnHeaderG2SOPL}" tooltip="{i18n>columnHeaderG2SOPL}" textAlign="Right"/>                                                                                                                                                       
									<table:template>                                                                                                                                                                                                                                      
										<Text wrapping="false"                                                                                                                                                                                                                               
											tooltip="{parts : [{path:'HierDatModel>GaapToStatOtherPL'}, {path:'HierDatModel>MainCurrency'}],type: 'sap.ui.model.type.Currency',formatOptions:{showMeasure: false}}"                                                                             
											text="{parts : [{path:'HierDatModel>GaapToStatOtherPL'}, {path:'HierDatModel>MainCurrency'}],type: 'sap.ui.model.type.Currency',formatOptions:{showMeasure: false}}"/>                                                                              
									</table:template>                                                                                                                                                                                                                                     
								</table:Column>                                                                                                                                                                                                                                        
								<table:Column autoResizable="true" hAlign="End">                                                                                                                                                                                                       
									<Label text="{i18n>columnHeaderG2SOPerm}" tooltip="{i18n>columnHeaderG2SOPerm}" textAlign="Right"/>                                                                                                                                                   
									<table:template>                                                                                                                                                                                                                                      
										<Text wrapping="false"                                                                                                                                                                                                                               
											tooltip="{parts : [{path:'HierDatModel>GaapToStatOtherPmnt'}, {path:'HierDatModel>MainCurrency'}],type: 'sap.ui.model.type.Currency',formatOptions:{showMeasure: false}}"                                                                           
											text="{parts : [{path:'HierDatModel>GaapToStatOtherPmnt'}, {path:'HierDatModel>MainCurrency'}],type: 'sap.ui.model.type.Currency',formatOptions:{showMeasure: false}}"/>                                                                            
									</table:template>                                                                                                                                                                                                                                     
								</table:Column>                                                                                                                                                                                                                                        
								<table:Column autoResizable="true" hAlign="End">                                                                                                                                                                                                       
									<Label text="{i18n>columnHeaderG2SOEq}" tooltip="{i18n>columnHeaderG2SOEq}" textAlign="Right"/>                                                                                                                                                       
									<table:template>                                                                                                                                                                                                                                      
										<Text wrapping="false"                                                                                                                                                                                                                               
											tooltip="{parts : [{path:'HierDatModel>GaapToStatOtherEQ'}, {path:'HierDatModel>MainCurrency'}],type: 'sap.ui.model.type.Currency',formatOptions:{showMeasure: false}}"                                                                             
											text="{parts : [{path:'HierDatModel>GaapToStatOtherEQ'}, {path:'HierDatModel>MainCurrency'}],type: 'sap.ui.model.type.Currency',formatOptions:{showMeasure: false}}"/>                                                                              
									</table:template>                                                                                                                                                                                                                                     
								</table:Column>                                                                                                                                                                                                                                        
								<table:Column autoResizable="true" hAlign="End">                                                                                                                                                                                                       
									<Label text="{i18n>columnHeaderG2SCTA}" tooltip="{i18n>columnHeaderG2SCTA}" textAlign="Right"/>                                                                                                                                                       
									<table:template>                                                                                                                                                                                                                                      
										<Text wrapping="false"                                                                                                                                                                                                                               
											tooltip="{parts : [{path:'HierDatModel>G2SCTA'}, {path:'HierDatModel>MainCurrency'}],type: 'sap.ui.model.type.Currency',formatOptions:{showMeasure: false}}"                                                                                        
											text="{parts : [{path:'HierDatModel>G2SCTA'}, {path:'HierDatModel>MainCurrency'}],type: 'sap.ui.model.type.Currency',formatOptions:{showMeasure: false}}"/>                                                                                         
									</table:template>                                                                                                                                                                                                                                     
								</table:Column>                                                                                                                                                                                                                                        
								<table:Column autoResizable="true" hAlign="End">                                                                                                                                                                                                       
									<Label text="{i18n>columnHeaderSTATOB}" tooltip="{i18n>columnHeaderSTATOB}" textAlign="Right"/>                                                                                                                                                       
									<table:template>                                                                                                                                                                                                                                      
										<Text wrapping="false"                                                                                                                                                                                                                               
											tooltip="{parts : [{path:'HierDatModel>StatOpeningBalance'}, {path:'HierDatModel>MainCurrency'}],type: 'sap.ui.model.type.Currency',formatOptions:{showMeasure: false}}"                                                                            
											text="{parts : [{path:'HierDatModel>StatOpeningBalance'}, {path:'HierDatModel>MainCurrency'}],type: 'sap.ui.model.type.Currency',formatOptions:{showMeasure: false}}"/>                                                                             
									</table:template>                                                                                                                                                                                                                                     
								</table:Column>                                                                                                                                                                                                                                        
								<table:Column autoResizable="true" hAlign="End">                                                                                                                                                                                                       
									<Label text="{i18n>columnHeaderSTATPYA}" tooltip="{i18n>columnHeaderSTATPYA}" textAlign="Right"/>                                                                                                                                                     
									<table:template>                                                                                                                                                                                                                                      
										<Text wrapping="false"                                                                                                                                                                                                                               
											tooltip="{parts : [{path:'HierDatModel>StatPYA'}, {path:'HierDatModel>MainCurrency'}],type: 'sap.ui.model.type.Currency',formatOptions:{showMeasure: false}}"                                                                                       
											text="{parts : [{path:'HierDatModel>StatPYA'}, {path:'HierDatModel>MainCurrency'}],type: 'sap.ui.model.type.Currency',formatOptions:{showMeasure: false}}"/>                                                                                        
									</table:template>                                                                                                                                                                                                                                     
								</table:Column>                                                                                                                                                                                                                                        
								<table:Column autoResizable="true" hAlign="End">                                                                                                                                                                                                       
									<Label text="{i18n>columnHeaderSTATYB}" tooltip="{i18n>columnHeaderSTATYB}" textAlign="Right"/>                                                                                                                                                       
									<table:template>                                                                                                                                                                                                                                      
										<Text wrapping="false"                                                                                                                                                                                                                               
											tooltip="{parts : [{path:'HierDatModel>StatYearBalance'}, {path:'HierDatModel>MainCurrency'}],type: 'sap.ui.model.type.Currency',formatOptions:{showMeasure: false}}"                                                                               
											text="{parts : [{path:'HierDatModel>StatYearBalance'}, {path:'HierDatModel>MainCurrency'}],type: 'sap.ui.model.type.Currency',formatOptions:{showMeasure: false}}"/>                                                                                
									</table:template>                                                                                                                                                                                                                                     
								</table:Column>                                                                                                                                                                                                                                        
								<table:Column autoResizable="true" hAlign="End">                                                                                                                                                                                                       
									<Label text="{i18n>columnHeaderSTATCTA}" tooltip="{i18n>columnHeaderSTATCTA}" textAlign="Right"/>                                                                                                                                                     
									<table:template>                                                                                                                                                                                                                                      
										<Text wrapping="false"                                                                                                                                                                                                                               
											tooltip="{parts : [{path:'HierDatModel>StatCTA'}, {path:'HierDatModel>MainCurrency'}],type: 'sap.ui.model.type.Currency',formatOptions:{showMeasure: false}}"                                                                                       
											text="{parts : [{path:'HierDatModel>StatCTA'}, {path:'HierDatModel>MainCurrency'}],type: 'sap.ui.model.type.Currency',formatOptions:{showMeasure: false}}"/>                                                                                        
									</table:template>                                                                                                                                                                                                                                     
								</table:Column>                                                                                                                                                                                                                                        
								<table:Column autoResizable="true" hAlign="End">                                                                                                                                                                                                       
									<Label text="{i18n>columnHeaderSTATCB}" tooltip="{i18n>columnHeaderSTATCB}" textAlign="Right"/>                                                                                                                                                       
									<table:template>                                                                                                                                                                                                                                      
										<Text wrapping="false"                                                                                                                                                                                                                               
											tooltip="{parts : [{path:'HierDatModel>StatClosingBalance'}, {path:'HierDatModel>MainCurrency'}],type: 'sap.ui.model.type.Currency',formatOptions:{showMeasure: false}}"                                                                            
											text="{parts : [{path:'HierDatModel>StatClosingBalance'}, {path:'HierDatModel>MainCurrency'}],type: 'sap.ui.model.type.Currency',formatOptions:{showMeasure: false}}"/>                                                                             
									</table:template>                                                                                                                                                                                                                                     
								</table:Column>                                                                                                                                                                                                                                        
								<table:Column autoResizable="true" hAlign="End">                                                                                                                                                                                                       
									<Label text="{i18n>columnHeaderS2TPL}" tooltip="{i18n>columnHeaderS2TPL}" textAlign="Right"/>                                                                                                                                                         
									<table:template>                                                                                                                                                                                                                                      
										<Text wrapping="false"                                                                                                                                                                                                                               
											tooltip="{parts : [{path:'HierDatModel>StatToTaxPL'}, {path:'HierDatModel>MainCurrency'}],type: 'sap.ui.model.type.Currency',formatOptions:{showMeasure: false}}"                                                                                   
											text="{parts : [{path:'HierDatModel>StatToTaxPL'}, {path:'HierDatModel>MainCurrency'}],type: 'sap.ui.model.type.Currency',formatOptions:{showMeasure: false}}"/>                                                                                    
									</table:template>                                                                                                                                                                                                                                     
								</table:Column>                                                                                                                                                                                                                                        
								<table:Column autoResizable="true" hAlign="End">                                                                                                                                                                                                       
									<Label text="{i18n>columnHeaderS2TPERM}" tooltip="{i18n>columnHeaderS2TPERM}" textAlign="Right"/>                                                                                                                                                     
									<table:template>                                                                                                                                                                                                                                      
										<Text wrapping="false"                                                                                                                                                                                                                               
											tooltip="{parts : [{path:'HierDatModel>StatToTaxPmnt'}, {path:'HierDatModel>MainCurrency'}],type: 'sap.ui.model.type.Currency',formatOptions:{showMeasure: false}}"                                                                                 
											text="{parts : [{path:'HierDatModel>StatToTaxPmnt'}, {path:'HierDatModel>MainCurrency'}],type: 'sap.ui.model.type.Currency',formatOptions:{showMeasure: false}}"/>                                                                                  
									</table:template>                                                                                                                                                                                                                                     
								</table:Column>                                                                                                                                                                                                                                        
								<table:Column autoResizable="true" hAlign="End">                                                                                                                                                                                                       
									<Label text="{i18n>columnHeaderS2TEQ}" tooltip="{i18n>columnHeaderS2TEQ}" textAlign="Right"/>                                                                                                                                                         
									<table:template>                                                                                                                                                                                                                                      
										<Text wrapping="false"                                                                                                                                                                                                                               
											tooltip="{parts : [{path:'HierDatModel>StatToTaxEQ'}, {path:'HierDatModel>MainCurrency'}],type: 'sap.ui.model.type.Currency',formatOptions:{showMeasure: false}}"                                                                                   
											text="{parts : [{path:'HierDatModel>StatToTaxEQ'}, {path:'HierDatModel>MainCurrency'}],type: 'sap.ui.model.type.Currency',formatOptions:{showMeasure: false}}"/>                                                                                    
									</table:template>                                                                                                                                                                                                                                     
								</table:Column>                                                                                                                                                                                                                                        
								<table:Column autoResizable="true" hAlign="End">                                                                                                                                                                                                       
									<Label text="{i18n>columnHeaderS2TOthPL}" tooltip="{i18n>columnHeaderS2TOthPL}" textAlign="Right"/>                                                                                                                                                   
									<table:template>                                                                                                                                                                                                                                      
										<Text wrapping="false"                                                                                                                                                                                                                               
											tooltip="{parts : [{path:'HierDatModel>StatToTaxOtherPL'}, {path:'HierDatModel>MainCurrency'}],type: 'sap.ui.model.type.Currency',formatOptions:{showMeasure: false}}"                                                                              
											text="{parts : [{path:'HierDatModel>StatToTaxOtherPL'}, {path:'HierDatModel>MainCurrency'}],type: 'sap.ui.model.type.Currency',formatOptions:{showMeasure: false}}"/>                                                                               
									</table:template>                                                                                                                                                                                                                                     
								</table:Column>                                                                                                                                                                                                                                        
								<table:Column autoResizable="true" hAlign="End">                                                                                                                                                                                                       
									<Label text="{i18n>columnHeaderS2TOthPERM}" tooltip="{i18n>columnHeaderS2TOthPERM}" textAlign="Right"/>                                                                                                                                               
									<table:template>                                                                                                                                                                                                                                      
										<Text wrapping="false"                                                                                                                                                                                                                               
											tooltip="{parts : [{path:'HierDatModel>StatToTaxOtherPmnt'}, {path:'HierDatModel>MainCurrency'}],type: 'sap.ui.model.type.Currency',formatOptions:{showMeasure: false}}"                                                                            
											text="{parts : [{path:'HierDatModel>StatToTaxOtherPmnt'}, {path:'HierDatModel>MainCurrency'}],type: 'sap.ui.model.type.Currency',formatOptions:{showMeasure: false}}"/>                                                                             
									</table:template>                                                                                                                                                                                                                                     
								</table:Column>                                                                                                                                                                                                                                        
								<table:Column autoResizable="true" hAlign="End">                                                                                                                                                                                                       
									<Label text="{i18n>columnHeaderS2TOthEQ}" tooltip="{i18n>columnHeaderS2TOthEQ}" textAlign="Right"/>                                                                                                                                                   
									<table:template>                                                                                                                                                                                                                                      
										<Text wrapping="false"                                                                                                                                                                                                                               
											tooltip="{parts : [{path:'HierDatModel>StatToTaxOtherEQ'}, {path:'HierDatModel>MainCurrency'}],type: 'sap.ui.model.type.Currency',formatOptions:{showMeasure: false}}"                                                                              
											text="{parts : [{path:'HierDatModel>StatToTaxOtherEQ'}, {path:'HierDatModel>MainCurrency'}],type: 'sap.ui.model.type.Currency',formatOptions:{showMeasure: false}}"/>                                                                               
									</table:template>                                                                                                                                                                                                                                     
								</table:Column>                                                                                                                                                                                                                                        
								<table:Column autoResizable="true" hAlign="End">                                                                                                                                                                                                       
									<Label text="{i18n>columnHeaderS2TCTA}" tooltip="{i18n>columnHeaderS2TCTA}" textAlign="Right"/>                                                                                                                                                       
									<table:template>                                                                                                                                                                                                                                      
										<Text wrapping="false"                                                                                                                                                                                                                               
											tooltip="{parts : [{path:'HierDatModel>S2TCTA'}, {path:'HierDatModel>MainCurrency'}],type: 'sap.ui.model.type.Currency',formatOptions:{showMeasure: false}}"                                                                                        
											text="{parts : [{path:'HierDatModel>S2TCTA'}, {path:'HierDatModel>MainCurrency'}],type: 'sap.ui.model.type.Currency',formatOptions:{showMeasure: false}}"/>                                                                                         
									</table:template>                                                                                                                                                                                                                                     
								</table:Column>                                                                                                                                                                                                                                        
								<table:Column autoResizable="true" hAlign="End">                                                                                                                                                                                                       
									<Label text="{i18n>columnHeaderTaxOB}" tooltip="{i18n>columnHeaderTaxOB}" textAlign="Right"/>                                                                                                                                                         
									<table:template>                                                                                                                                                                                                                                      
										<Text wrapping="false"                                                                                                                                                                                                                               
											tooltip="{parts : [{path:'HierDatModel>TaxOpeningBalance'}, {path:'HierDatModel>MainCurrency'}],type: 'sap.ui.model.type.Currency',formatOptions:{showMeasure: false}}"                                                                             
											text="{parts : [{path:'HierDatModel>TaxOpeningBalance'}, {path:'HierDatModel>MainCurrency'}],type: 'sap.ui.model.type.Currency',formatOptions:{showMeasure: false}}"/>                                                                              
									</table:template>                                                                                                                                                                                                                                     
								</table:Column>                                                                                                                                                                                                                                        
								<table:Column autoResizable="true" hAlign="End">                                                                                                                                                                                                       
									<Label text="{i18n>columnHeaderTaxPYA}" tooltip="{i18n>columnHeaderTaxPYA}" textAlign="Right"/>                                                                                                                                                       
									<table:template>                                                                                                                                                                                                                                      
										<Text wrapping="false"                                                                                                                                                                                                                               
											tooltip="{parts : [{path:'HierDatModel>TaxPYA'}, {path:'HierDatModel>MainCurrency'}],type: 'sap.ui.model.type.Currency',formatOptions:{showMeasure: false}}"                                                                                        
											text="{parts : [{path:'HierDatModel>TaxPYA'}, {path:'HierDatModel>MainCurrency'}],type: 'sap.ui.model.type.Currency',formatOptions:{showMeasure: false}}"/>                                                                                         
									</table:template>                                                                                                                                                                                                                                     
								</table:Column>                                                                                                                                                                                                                                        
								<table:Column autoResizable="true" hAlign="End">                                                                                                                                                                                                       
									<Label text="{i18n>columnHeaderTaxYB}" tooltip="{i18n>columnHeaderTaxYB}" textAlign="Right"/>                                                                                                                                                         
									<table:template>                                                                                                                                                                                                                                      
										<Text wrapping="false"                                                                                                                                                                                                                               
											tooltip="{parts : [{path:'HierDatModel>TaxYearBalance'}, {path:'HierDatModel>MainCurrency'}],type: 'sap.ui.model.type.Currency',formatOptions:{showMeasure: false}}"                                                                                
											text="{parts : [{path:'HierDatModel>TaxYearBalance'}, {path:'HierDatModel>MainCurrency'}],type: 'sap.ui.model.type.Currency',formatOptions:{showMeasure: false}}"/>                                                                                 
									</table:template>                                                                                                                                                                                                                                     
								</table:Column>                                                                                                                                                                                                                                        
								<table:Column autoResizable="true" hAlign="End">                                                                                                                                                                                                       
									<Label text="{i18n>columnHeaderTaxCTA}" tooltip="{i18n>columnHeaderTaxCTA}" textAlign="Right"/>                                                                                                                                                       
									<table:template>                                                                                                                                                                                                                                      
										<Text wrapping="false"                                                                                                                                                                                                                               
											tooltip="{parts : [{path:'HierDatModel>TaxCTA'}, {path:'HierDatModel>MainCurrency'}],type: 'sap.ui.model.type.Currency',formatOptions:{showMeasure: false}}"                                                                                        
											text="{parts : [{path:'HierDatModel>TaxCTA'}, {path:'HierDatModel>MainCurrency'}],type: 'sap.ui.model.type.Currency',formatOptions:{showMeasure: false}}"/>                                                                                         
									</table:template>                                                                                                                                                                                                                                     
								</table:Column>                                                                                                                                                                                                                                        
								<table:Column autoResizable="true" hAlign="End">                                                                                                                                                                                                       
									<Label text="{i18n>columnHeaderTaxCB}" tooltip="{i18n>columnHeaderTaxCB}" textAlign="Right"/>                                                                                                                                                         
									<table:template>                                                                                                                                                                                                                                      
										<Text wrapping="false"                                                                                                                                                                                                                               
											tooltip="{parts : [{path:'HierDatModel>TaxClosingBalance'}, {path:'HierDatModel>MainCurrency'}],type: 'sap.ui.model.type.Currency',formatOptions:{showMeasure: false}}"                                                                             
											text="{parts : [{path:'HierDatModel>TaxClosingBalance'}, {path:'HierDatModel>MainCurrency'}],type: 'sap.ui.model.type.Currency',formatOptions:{showMeasure: false}}"/>                                                                              
									</table:template>                                                                                                                                                                                                                                     
								</table:Column>                                                                                                                                                                                                                                        
								<table:Column autoResizable="true" hAlign="End">                                                                                                                                                                                                       
									<Label text="{i18n>columnHeaderPTA}" tooltip="{i18n>columnHeaderPTA}" textAlign="Right"/>                                                                                                                                                             
									<table:template>                                                                                                                                                                                                                                      
										<Text wrapping="false"                                                                                                                                                                                                                               
											tooltip="{parts : [{path:'HierDatModel>TaxPTA'}, {path:'HierDatModel>MainCurrency'}],type: 'sap.ui.model.type.Currency',formatOptions:{showMeasure: false}}"                                                                                        
											text="{parts : [{path:'HierDatModel>TaxPTA'}, {path:'HierDatModel>MainCurrency'}],type: 'sap.ui.model.type.Currency',formatOptions:{showMeasure: false}}"/>                                                                                         
									</table:template>                                                                                                                                                                                                                                     
								</table:Column>                                                                                                                                                                                                                                        
							</table:TreeTable>                                                                                                                                                                                                                                      
						</smartTable:SmartTable>                                                                                                                                                                                                                                 
					</uxap:ObjectPageSubSection>                                                                                                                                                                                                                              
				</uxap:subSections>                                                                                                                                                                                                                                        
			</uxap:ObjectPageSection>                                                                                                                                                                                                                                   
			<uxap:ObjectPageSection titleUppercase="false" title="{i18n>GLAccVHText}">                                                                                                                                                                                  
				<uxap:subSections>                                                                                                                                                                                                                                         
					<uxap:ObjectPageSubSection id="idGEPageSubSection" title="{i18n>GLAccVHText}" titleUppercase="false">                                                                                                                                                     
						<Label text="Upcoming Section"></Label>                                                                                                                                                                                                                  
					</uxap:ObjectPageSubSection>                                                                                                                                                                                                                              
				</uxap:subSections>                                                                                                                                                                                                                                        
			</uxap:ObjectPageSection>                                                                                                                                                                                                                                   
		</uxap:sections>                                                                                                                                                                                                                                             
	</uxap:ObjectPageLayout>                                                                                                                                                                                                                                      
</mvc:View>                                                                                                                                                                                                                                                    